test_packaging_test_packaging/__init__.py
test_packaging_test_packaging/main.py
test_packaging_test_packaging-0.1.0.dist-info/METADATA
test_packaging_test_packaging-0.1.0.dist-info/WHEEL
test_packaging_test_packaging-0.1.0.dist-info/RECORD
