Metadata-Version: 2.1
Name: test-packaging-test-packaging
Version: 0.1.0
Summary: 
Author: Alc-Alc
Author-email: alc@example.com
Requires-Python: >=3.12,<4.0
Classifier: Programming Language :: Python :: 3
Classifier: Programming Language :: Python :: 3.12
Requires-Dist: litestar (>=2.5.4,<3.0.0)
